greylock/__init__.py
greylock/__main__.py
greylock/abundance.py
greylock/components.py
greylock/exceptions.py
greylock/log.py
greylock/metacommunity.py
greylock/parameters.py
greylock/powermean.py
greylock/ray.py
greylock/similarity.py
greylock/tests/mockray.py
greylock/tests/mockray_test.py
greylock/tests/ray_test.py
greylock/tests/base_tests/abundance_test.py
greylock/tests/base_tests/components_test.py
greylock/tests/base_tests/main_test.py
greylock/tests/base_tests/metacommunity_test.py
greylock/tests/base_tests/parameters_test.py
greylock/tests/base_tests/powermean_test.py
greylock/tests/base_tests/similarity_test.py
greylock-1.1.0.dist-info/METADATA
greylock-1.1.0.dist-info/WHEEL
greylock-1.1.0.dist-info/licenses/LICENSE
greylock-1.1.0.dist-info/RECORD
