Metadata-Version: 2.4
Name: greylock
Version: 1.1.0
Summary: A Python package for measuring the composition of complex datasets
Project-URL: Homepage, https://github.com/ArnaoutLab/diversity
Project-URL: Bug Tracker, https://github.com/ArnaoutLab/diversity/issues
Author-email: Elliot Hill <elliot.douglas.hill@gmail.com>, Alex Morgan <amorgan2@bidmc.harvard.edu>, Phuc Nguyen <pnguye10@bidmc.harvard.edu>, Jasper Braun <jasperbraun90@gmail.com>
Maintainer-email: Alex Morgan <amorgan2@bidmc.harvard.edu>
License-File: LICENSE
Classifier: License :: OSI Approved :: MIT License
Classifier: Operating System :: OS Independent
Classifier: Programming Language :: Python :: 3
Requires-Python: >=3.9
Requires-Dist: numpy>=1.24.0
Requires-Dist: pandas>=1.5.2
Requires-Dist: scipy>=1.10.0
Provides-Extra: lint
Requires-Dist: black>=24.3.0; extra == 'lint'
Provides-Extra: ray
Requires-Dist: ray>=2.42.1; extra == 'ray'
Provides-Extra: tests
Requires-Dist: pytest-cov>=3.0.0; extra == 'tests'
Requires-Dist: pytest>=7.2.1; extra == 'tests'
